serial_toolbox/__init__.py
serial_toolbox/connect.py
serial_toolbox/gui.py
serial_toolbox/interface_core.py
serial_toolbox/log_init.py
serial_toolbox-0.1.5.dist-info/entry_points.txt
serial_toolbox-0.1.5.dist-info/LICENSE
serial_toolbox-0.1.5.dist-info/METADATA
serial_toolbox-0.1.5.dist-info/WHEEL
serial_toolbox-0.1.5.dist-info/RECORD
