Metadata-Version: 2.1
Name: serial_toolbox
Version: 0.1.5
Summary: Utility functions for pySerial
License: Apache-2.0
Author: Takuya Sasatani
Author-email: 33111879+t-sasatani@users.noreply.github.com
Requires-Python: >=3.10,<4.0
Classifier: License :: OSI Approved :: Apache Software License
Classifier: Programming Language :: Python :: 3
Classifier: Programming Language :: Python :: 3.10
Classifier: Programming Language :: Python :: 3.11
Requires-Dist: coloredlogs (>=15.0.1,<16.0.0)
Requires-Dist: customtkinter (>=5.2.2,<6.0.0)
Requires-Dist: matplotlib (>=3.8.4,<4.0.0)
Requires-Dist: myst-parser (>=2.0.0,<3.0.0)
Requires-Dist: pyserial (>=3.5,<4.0)
Requires-Dist: sphinx (>=7.2.6,<8.0.0)
Requires-Dist: sphinx-rtd-theme (>=2.0.0,<3.0.0)
